LICENSE
MANIFEST.in
README.md
pyproject.toml
requirements.analyze.txt
requirements.documentation.txt
requirements.test.txt
requirements.txt
setup.py
sampledb/__init__.py
sampledb/__main__.py
sampledb/config.py
sampledb/dashboard.py
sampledb/utils.py
sampledb/version.py
sampledb.egg-info/PKG-INFO
sampledb.egg-info/SOURCES.txt
sampledb.egg-info/dependency_links.txt
sampledb.egg-info/requires.txt
sampledb.egg-info/top_level.txt
sampledb/api/__init__.py
sampledb/api/utils.py
sampledb/api/federation/__init__.py
sampledb/api/federation/authentication.py
sampledb/api/federation/federation.py
sampledb/api/frontend/__init__.py
sampledb/api/frontend/favorites.py
sampledb/api/server/__init__.py
sampledb/api/server/action_types.py
sampledb/api/server/actions.py
sampledb/api/server/authentication.py
sampledb/api/server/comments.py
sampledb/api/server/errors.py
sampledb/api/server/files.py
sampledb/api/server/groups.py
sampledb/api/server/instrument_log.py
sampledb/api/server/instruments.py
sampledb/api/server/locations.py
sampledb/api/server/object_log.py
sampledb/api/server/object_permissions.py
sampledb/api/server/objects.py
sampledb/api/server/projects.py
sampledb/api/server/users.py
sampledb/frontend/__init__.py
sampledb/frontend/action_types.py
sampledb/frontend/actions.py
sampledb/frontend/admin_warnings.py
sampledb/frontend/authentication_forms.py
sampledb/frontend/background_tasks.py
sampledb/frontend/dataverse_export.py
sampledb/frontend/download_service.py
sampledb/frontend/eln_import.py
sampledb/frontend/errors.py
sampledb/frontend/export.py
sampledb/frontend/favicon.py
sampledb/frontend/federation.py
sampledb/frontend/federation_forms.py
sampledb/frontend/group_categories.py
sampledb/frontend/index.py
sampledb/frontend/info_pages.py
sampledb/frontend/instruments.py
sampledb/frontend/labels.py
sampledb/frontend/languages.py
sampledb/frontend/location_types.py
sampledb/frontend/locations.py
sampledb/frontend/markdown_images.py
sampledb/frontend/pdfexport.py
sampledb/frontend/permission_forms.py
sampledb/frontend/projects.py
sampledb/frontend/projects_forms.py
sampledb/frontend/publications.py
